{"mc":{
	"start13":{
		"frameRate":24,
		"labels":[
			{"name":"start13","frame":1,"end":6}
			
			],
		"events":[
			
			],
		"frames":[
			
			{
			"res":"FB4F6CA8",
			"x":0,
			"y":0
			},
			{
			"res":"1C40A007",
			"x":0,
			"y":0
			},
			{
			"res":"52503019",
			"x":0,
			"y":0
			},
			{
			"res":"6B0DDCEE",
			"x":0,
			"y":0
			},
			{
			"res":"405A1352",
			"x":0,
			"y":0
			},
			{
			"res":"F35F5A43",
			"x":0,
			"y":0
			}
			]
}},
	"res":{
		"52503019":{"x":2,"y":2,"w":960,"h":640},
		"1C40A007":{"x":966,"y":2,"w":960,"h":640},
		"6B0DDCEE":{"x":2,"y":646,"w":960,"h":640},
		"F35F5A43":{"x":966,"y":646,"w":960,"h":640},
		"FB4F6CA8":{"x":2,"y":1290,"w":960,"h":640},
		"405A1352":{"x":966,"y":1290,"w":960,"h":640}
	}}